LICENSE
README.md
setup.py
OrangePi.ILI9341.egg-info/PKG-INFO
OrangePi.ILI9341.egg-info/SOURCES.txt
OrangePi.ILI9341.egg-info/dependency_links.txt
OrangePi.ILI9341.egg-info/requires.txt
OrangePi.ILI9341.egg-info/top_level.txt
OrangePi_ILI9341/__init__.py